xdow/xdow.py
xdow-1.7.dist-info/LICENSE.txt
xdow-1.7.dist-info/METADATA
xdow-1.7.dist-info/WHEEL
xdow-1.7.dist-info/entry_points.txt
xdow-1.7.dist-info/top_level.txt
xdow-1.7.dist-info/RECORD
