Metadata-Version: 2.1
Name: xdow
Version: 1.7
Summary: Adult video downloader
Home-page: UNKNOWN
Author: pankaj kumar
Author-email: pkumdev@gmail.com
License: UNKNOWN
Platform: UNKNOWN
Requires-Dist: js2py
Requires-Dist: requests
Requires-Dist: bs4
Requires-Dist: wheel
